integral/__init__.py
integral/integral.py
integral/integral_vec.py
ode/__init__.py
ode/ode.py
root/__init__.py
root/root.py
nampyPrj-0.1.0.dist-info/METADATA
nampyPrj-0.1.0.dist-info/WHEEL
nampyPrj-0.1.0.dist-info/top_level.txt
nampyPrj-0.1.0.dist-info/RECORD
