Metadata-Version: 2.1
Name: nampyPrj
Version: 0.1.0
Summary: Demo Numerical Analysis library
Home-page: https://github.com/GiordiR/nampy
Author: Riccardo Giordani
Author-email: riccardo.giordani93@gmail.com
License: MIT
Platform: UNKNOWN
Classifier: Intended Audience :: Developers
Classifier: License :: OSI Approved :: MIT License
Classifier: Programming Language :: Python :: 3.10
Classifier: Operating System :: OS Independent
Requires-Dist: numpy
Requires-Dist: sympy
Requires-Dist: matplotlib
